calories.py
calories-0.1.0.dist-info/METADATA
calories-0.1.0.dist-info/WHEEL
calories-0.1.0.dist-info/entry_points.txt
calories-0.1.0.dist-info/top_level.txt
calories-0.1.0.dist-info/RECORD
